randomness_xiatthew/__init__.py
randomness_xiatthew-0.0.9.dist-info/METADATA
randomness_xiatthew-0.0.9.dist-info/WHEEL
randomness_xiatthew-0.0.9.dist-info/entry_points.txt
randomness_xiatthew-0.0.9.dist-info/top_level.txt
randomness_xiatthew-0.0.9.dist-info/RECORD
