Metadata-Version: 2.1
Name: randomness-xiatthew
Version: 0.0.9
Summary: Say Hello World
Author: Xiatthew
Author-email: neosphere.matthewxia@gmail.com
License: UNKNOWN
Platform: UNKNOWN
Classifier: Programming Language :: Python :: 3
Classifier: License :: Freeware
Classifier: Operating System :: MacOS
Requires-Python: >=3.6
